docmd/__init__.py
docmd/__main__.py
docmd/docmd.py
docmd-1.0.6.dist-info/LICENSE
docmd-1.0.6.dist-info/METADATA
docmd-1.0.6.dist-info/WHEEL
docmd-1.0.6.dist-info/entry_points.txt
docmd-1.0.6.dist-info/top_level.txt
docmd-1.0.6.dist-info/RECORD
