Metadata-Version: 2.1
Name: docmd
Version: 1.0.6
Summary: Convert python docstring documentation to github markdown files
Home-page: https://github.com/AtakamaLLC/docmd
License: UNKNOWN
Platform: UNKNOWN
